s3_concat/__init__.py
s3_concat/cli.py
s3_concat/multipart_upload_job.py
s3_concat/utils.py
s3_concat-0.3.0.dist-info/licenses/LICENSE
s3_concat-0.3.0.dist-info/METADATA
s3_concat-0.3.0.dist-info/WHEEL
s3_concat-0.3.0.dist-info/entry_points.txt
s3_concat-0.3.0.dist-info/top_level.txt
s3_concat-0.3.0.dist-info/RECORD
