Metadata-Version: 2.4
Name: s3-concat
Version: 0.3.0
Summary: Concat files in s3
Author-email: Eddy Hintze <eddy@gitx.codes>
License: The MIT License (MIT)
Project-URL: Homepage, https://github.com/xtream1101/s3-concat
Classifier: Programming Language :: Python :: 3
Classifier: License :: OSI Approved :: MIT License
Classifier: Operating System :: OS Independent
Classifier: Topic :: Software Development :: Libraries :: Python Modules
Classifier: Topic :: Utilities
Requires-Python: >=3.8
License-File: LICENSE
Requires-Dist: boto3
Dynamic: license-file
